{
    "/js/agenda.js": "/js/agenda.js?id=d4e03f6d91e69d15debb",
    "/css/amsterdam/flipclock.css": "/css/amsterdam/flipclock.css?id=32fdfe1d2a4f30970a08",
    "/css/london/flipclock.css": "/css/london/flipclock.css?id=598b4a67c2063b0e358b",
    "/css/404.css": "/css/404.css?id=0717d426617d1c27884a",
    "/css/lasvegas/flipclock.css": "/css/lasvegas/flipclock.css?id=4bd37f6aa206e587d174",
    "/css/global/press.css": "/css/global/press.css?id=b1aa9cc73553375052c4",
    "/css/global/about.css": "/css/global/about.css?id=1fd7b3d2488a6a882929",
    "/css/header-footer.css": "/css/header-footer.css?id=6e2316c5967d7f87e378",
    "/css/global/startup.css": "/css/global/startup.css?id=135e7b56214072c1ddb7",
    "/css/global/holiday.css": "/css/global/holiday.css?id=20039ff3d251ce402329",
    "/css/amsterdam/about.css": "/css/amsterdam/about.css?id=14ecb6d0238fffa5444c",
    "/css/amsterdam/index.css": "/css/amsterdam/index.css?id=8ce0f7fc36de5824ebec",
    "/css/amsterdam/speaker.css": "/css/amsterdam/speaker.css?id=18b2c3d816f8485f6bf7",
    "/css/amsterdam/speakers.css": "/css/amsterdam/speakers.css?id=e4f652332abea9d9598f",
    "/css/amsterdam/sponsor.css": "/css/amsterdam/sponsor.css?id=427aa4d799481e137148",
    "/css/amsterdam/sponsors.css": "/css/amsterdam/sponsors.css?id=89bd85688a10081010da",
    "/css/amsterdam/venue.css": "/css/amsterdam/venue.css?id=d89462c2925f2dab98d5",
    "/css/amsterdam/agenda.css": "/css/amsterdam/agenda.css?id=ea173c064fdcda9d05b2",
    "/css/amsterdam/terms.css": "/css/amsterdam/terms.css?id=8ae52846822d3bb9bcd3",
    "/css/amsterdam/tickets_temp.css": "/css/amsterdam/tickets_temp.css?id=ccf66146b125c30d69c0",
    "/css/amsterdam/tickets_old.css": "/css/amsterdam/tickets_old.css?id=c2211b51cc1928681499",
    "/css/amsterdam/pdfs.css": "/css/amsterdam/pdfs.css?id=dec1aba6c39cb8023ace",
    "/css/lasvegas/about.css": "/css/lasvegas/about.css?id=682c949729bbdba92185",
    "/css/lasvegas/index.css": "/css/lasvegas/index.css?id=cf5ea918634b20c8b5d1",
    "/css/lasvegas/speaker.css": "/css/lasvegas/speaker.css?id=482dbdbda73adcba0a9e",
    "/css/lasvegas/speakers.css": "/css/lasvegas/speakers.css?id=11c7ca9e3292cd582e31",
    "/css/lasvegas/sponsor.css": "/css/lasvegas/sponsor.css?id=04a78440caa17f580dc1",
    "/css/lasvegas/sponsors.css": "/css/lasvegas/sponsors.css?id=419f51947268a208b47f",
    "/css/lasvegas/venue.css": "/css/lasvegas/venue.css?id=f810957e22e2776dee9c",
    "/css/lasvegas/floorplan_new.css": "/css/lasvegas/floorplan_new.css?id=b2ffc56bf08e3d7641e5",
    "/css/lasvegas/travel.css": "/css/lasvegas/travel.css?id=94673a91cae9f05b2d84",
    "/css/lasvegas/volunteer.css": "/css/lasvegas/volunteer.css?id=af2dac2d606d69ddad58",
    "/css/lasvegas/startup.css": "/css/lasvegas/startup.css?id=e827bcb1abc3dd84b986",
    "/css/lasvegas/tickets_temp.css": "/css/lasvegas/tickets_temp.css?id=3403ae533f053dea4e7d",
    "/css/lasvegas/tickets_old.css": "/css/lasvegas/tickets_old.css?id=3ca2f757526a1bc28f08",
    "/css/lasvegas/pdfs.css": "/css/lasvegas/pdfs.css?id=cd97a6992f11e8121bfe",
    "/css/london/index.css": "/css/london/index.css?id=8a8fd7c6eb93c03c84a9",
    "/css/london/speaker.css": "/css/london/speaker.css?id=45d9cac23b885831dd18",
    "/css/london/speakers.css": "/css/london/speakers.css?id=13a83f4568dced6eadf9",
    "/css/london/sponsor.css": "/css/london/sponsor.css?id=824a7c9cd9c03cdd0576",
    "/css/london/sponsors.css": "/css/london/sponsors.css?id=69297eb81420e8cd0d79",
    "/css/london/venue.css": "/css/london/venue.css?id=d2b308cd34ac496ae3a1",
    "/css/london/startup.css": "/css/london/startup.css?id=a742f69edc405ec561f0",
    "/css/london/travel.css": "/css/london/travel.css?id=fc365b7708d3112fa829",
    "/css/london/volunteer.css": "/css/london/volunteer.css?id=90f188580c8520e53053",
    "/css/london/loyalty.css": "/css/london/loyalty.css?id=99eb89e77d79e140b322",
    "/css/london/speakergrid-travel.css": "/css/london/speakergrid-travel.css?id=5c738755b83784a26175",
    "/css/london/tickets_temp.css": "/css/london/tickets_temp.css?id=21cc8026b0bbe650707b",
    "/css/london/tickets_old.css": "/css/london/tickets_old.css?id=2cbac16a9c2337bc25ba",
    "/css/london/pdfs.css": "/css/london/pdfs.css?id=f4167c67fe94d6553ede",
    "/css/london/agenda.css": "/css/london/agenda.css?id=f457e79598db63d93bdb",
    "/css/london/agenda_beta.css": "/css/london/agenda_beta.css?id=8ef697e891180c6dfb4a",
    "/css/london/agenda-v2.css": "/css/london/agenda-v2.css?id=4810991543f271a5bf5a",
    "/js/minrequire.js": "/js/minrequire.js?id=a08cc3329f14029fed5b",
    "/js/amsterdam/unleash-amsterdam.js": "/js/amsterdam/unleash-amsterdam.js?id=503889c763c7e23fc9a0",
    "/js/london/responsiveslides.js": "/js/london/responsiveslides.js?id=b8b5816f67a6d93c73a0",
    "/js/london/main.js": "/js/london/main.js?id=436d6af18aeb241bab9d",
    "/js/london/flipclock.min.js": "/js/london/flipclock.min.js?id=b6c0bab9a6538d1f1cde",
    "/js/london/agenda.js": "/js/london/agenda.js?id=0d02817add1179096575",
    "/js/lasvegas/responsiveslides.js": "/js/lasvegas/responsiveslides.js?id=5bb9c185f98dcb7caba0",
    "/js/lasvegas/main.js": "/js/lasvegas/main.js?id=f14c9105d3e8d137a69a",
    "/js/amsterdam/main.js": "/js/amsterdam/main.js?id=144b08f3a153419681b6",
    "/js/amsterdam/flipclock.min.js": "/js/amsterdam/flipclock.min.js?id=977beac9d036662103ff"
}